usso_jwt/__init__.py
usso_jwt/config.py
usso_jwt/enums.py
usso_jwt/exceptions.py
usso_jwt/py.typed
usso_jwt/schemas.py
usso_jwt/sign.py
usso_jwt/utils.py
usso_jwt/verify.py
usso_jwt/algorithms/__init__.py
usso_jwt/algorithms/base.py
usso_jwt/algorithms/ecdsa.py
usso_jwt/algorithms/eddsa.py
usso_jwt/algorithms/hmac.py
usso_jwt/algorithms/rsa.py
usso_jwt-0.2.10.dist-info/licenses/LICENSE.txt
usso_jwt-0.2.10.dist-info/METADATA
usso_jwt-0.2.10.dist-info/WHEEL
usso_jwt-0.2.10.dist-info/top_level.txt
usso_jwt-0.2.10.dist-info/RECORD
