Metadata-Version: 2.4
Name: usso-jwt
Version: 0.2.10
Summary: A simple and lightweight Python package for handling JWT (JSON Web Token) operations with USSO (Unified Single Sign-On).
Author-email: Mahdi Kiani <mahdikiany@gmail.com>
Maintainer-email: Mahdi Kiani <mahdikiany@gmail.com>
License-Expression: MIT
Project-URL: Homepage, https://github.com/ussoio/usso-jwt
Project-URL: Bug Reports, https://github.com/ussoio/usso-jwt/issues
Project-URL: Funding, https://github.com/ussoio/usso-jwt
Project-URL: Say Thanks!, https://saythanks.io/to/mahdikiani
Project-URL: Source, https://github.com/ussoio/usso-jwt
Keywords: usso,usso-jwt,sso,authentication,security,jwt,json-web-token,token
Classifier: Development Status :: 3 - Alpha
Classifier: Intended Audience :: Developers
Classifier: Topic :: Software Development :: Build Tools
Classifier: Programming Language :: Python :: 3
Classifier: Programming Language :: Python :: 3.10
Classifier: Programming Language :: Python :: 3.11
Classifier: Programming Language :: Python :: 3.12
Classifier: Programming Language :: Python :: 3 :: Only
Requires-Python: >=3.9
License-File: LICENSE.txt
Requires-Dist: pydantic>=2
Requires-Dist: json-advanced
Requires-Dist: httpx
Requires-Dist: cryptography
Requires-Dist: cachetools>=5.0.0
Dynamic: license-file
